{
  "40fb4655-c62c-4372-8e41-4f80e48e6fcf_0": {
    "id": "40fb4655-c62c-4372-8e41-4f80e48e6fcf_0",
    "datasetId": "40fb4655-c62c-4372-8e41-4f80e48e6fcf",
    "content": "魹ｽ魹ｽ魹ｽ魹ｽ魹ｽ魹ｽﾒｻ魹ｽ魹ｽ魹ｽﾔｸ魹ｽﾑｪ魹ｽ魹ｽﾎｪ魹ｽ魹ｽ魹ｽ魹ｽ魹ｽﾄｴ魹ｽﾐｻ魹ｽﾔｼ魹ｽ魹ｽ魹ｽ魹ｽ魹ｽ魹ｽ魹ｽﾑｪ魹ｽ魹ｽ魹ｽ魹ｽ魹ｽ魹ｽ魹ｽ魹ｽ魹ｽ魹ｽ魹ｽﾈｵ魹ｽ魹ｽﾘｷ魹ｽ魹ｽ魹ｽﾈｱ魹ｽﾝｻ魹ｽ魹ｽ魹ｽ魹ｽ魹ｽ魹ｽ魹ｽ魹ｽ魹ｽ魹ｽ魹ｽ魹ｽﾏｰ魹ｽ魹ｽ魹ｽ魹ｽ魹ｽ魹ｽ魹ｽ魹ｽﾟｼ魹ｽ魹ｽ魹ｽ魹ｽ魹ｽ魹ｽ魹ｽ魹ｽ魹ｽ魹ｽ魹ｽﾊｱ魹ｽ魹ｽ魹ｽﾚｴ魹ｽ魹ｽﾚｵﾄｸ魹ｽﾑｪ魹ｽﾇ｣魹ｽ魹ｽ魹ｽ魹ｽﾂｸ魹ｽ魹ｽ魹ｽ魹ｽ魹ｽﾖｯ魹ｽ魹ｽ魹ｽﾘｱ魹ｽ魹ｽ魹ｽ魹ｽﾛ｡魹ｽ魹ｽ魹ｽ魹ｽ魹ｽ魹ｽ魹ｽ魹ｽ爍｢ﾑｪ魹ｽﾜ｡魹ｽ魹ｽ嘰ｭｵ魹ｽ魹ｽ魹ｽ魹ｽ魹ｽ魹ｽ岈ｦ｡魹ｽ魹ｽ魹ｽ魹ｽ魹ｽ魹ｽﾏｰ魹ｽ魹ｽ魹ｽ",
    "timestamp": "2026-06-01T09:11:47.553Z"
  }
}